[
    {
        "run": "01",
        "cycles": 127193643689,
        "instructions": 153463117362,
        "cache-references": 8576936228,
        "cache-misses": 1050300415,
        "branch-instructions": 28914822637,
        "branch-misses": 663575699,
        "time_elapsed": 4.102966132,
        "user_time": 28.278618,
        "sys_time": 2.380861,
        "insn_per_cycle": 1.21
    },
    {
        "run": "02",
        "cycles": 121295499363,
        "instructions": 147673108426,
        "cache-references": 8363868545,
        "cache-misses": 1010206415,
        "branch-instructions": 27642091874,
        "branch-misses": 609132745,
        "time_elapsed": 4.112120608,
        "user_time": 26.841806,
        "sys_time": 2.318845,
        "insn_per_cycle": 1.22
    },
    {
        "run": "03",
        "cycles": 118322612284,
        "instructions": 141359376157,
        "cache-references": 8378656894,
        "cache-misses": 1000485671,
        "branch-instructions": 26418779108,
        "branch-misses": 604331914,
        "time_elapsed": 4.08455771,
        "user_time": 26.157863,
        "sys_time": 2.332191,
        "insn_per_cycle": 1.19
    },
    {
        "run": "04",
        "cycles": 113282175998,
        "instructions": 136663859886,
        "cache-references": 8235076535,
        "cache-misses": 955949392,
        "branch-instructions": 25635788486,
        "branch-misses": 589103348,
        "time_elapsed": 3.966209296,
        "user_time": 24.944196,
        "sys_time": 2.319962,
        "insn_per_cycle": 1.21
    },
    {
        "run": "05",
        "cycles": 130865064022,
        "instructions": 137994218820,
        "cache-references": 9193070839,
        "cache-misses": 977113451,
        "branch-instructions": 25886850363,
        "branch-misses": 639687019,
        "time_elapsed": 2.979589863,
        "user_time": 31.205945,
        "sys_time": 3.43809,
        "insn_per_cycle": 1.05
    },
    {
        "run": "06",
        "cycles": 19350536389,
        "instructions": 39158857863,
        "cache-references": 648080652,
        "cache-misses": 76293302,
        "branch-instructions": 7463065502,
        "branch-misses": 209201709,
        "time_elapsed": 1.316426654,
        "user_time": 3.395866,
        "sys_time": 1.02415,
        "insn_per_cycle": 2.02
    },
    {
        "run": "07",
        "cycles": 22290780183,
        "instructions": 39675862134,
        "cache-references": 715262702,
        "cache-misses": 96210542,
        "branch-instructions": 7559310548,
        "branch-misses": 223202992,
        "time_elapsed": 0.872419973,
        "user_time": 4.015207,
        "sys_time": 1.401861,
        "insn_per_cycle": 1.78
    },
    {
        "run": "08",
        "cycles": 30635854285,
        "instructions": 33770052381,
        "cache-references": 644110214,
        "cache-misses": 142113204,
        "branch-instructions": 6077134521,
        "branch-misses": 165829987,
        "time_elapsed": 0.9698027,
        "user_time": 6.432534,
        "sys_time": 0.811932,
        "insn_per_cycle": 1.1
    },
    {
        "run": "09",
        "cycles": 14140618156,
        "instructions": 29326108418,
        "cache-references": 341492597,
        "cache-misses": 39691660,
        "branch-instructions": 5429958338,
        "branch-misses": 127241445,
        "time_elapsed": 0.533432225,
        "user_time": 2.916478,
        "sys_time": 0.448998,
        "insn_per_cycle": 2.07
    },
    {
        "run": "10",
        "cycles": 13817771306,
        "instructions": 29289349881,
        "cache-references": 336032223,
        "cache-misses": 38521524,
        "branch-instructions": 5437066258,
        "branch-misses": 126749587,
        "time_elapsed": 0.512617646,
        "user_time": 2.884872,
        "sys_time": 0.412697,
        "insn_per_cycle": 2.12
    },
    {
        "run": "11",
        "cycles": 16918909225,
        "instructions": 38345165070,
        "cache-references": 361110301,
        "cache-misses": 32971000,
        "branch-instructions": 6823734649,
        "branch-misses": 128037854,
        "time_elapsed": 0.570030622,
        "user_time": 3.70656,
        "sys_time": 0.442094,
        "insn_per_cycle": 2.27
    },
    {
        "run": "12",
        "cycles": 16576319935,
        "instructions": 36944409521,
        "cache-references": 369311571,
        "cache-misses": 34010294,
        "branch-instructions": 6516706510,
        "branch-misses": 128998928,
        "time_elapsed": 0.576544024,
        "user_time": 3.581679,
        "sys_time": 0.482573,
        "insn_per_cycle": 2.23
    }
]